daplis/__init__.py
daplis/functions/__init__.py
daplis/functions/calc_diff.py
daplis/functions/calibrate.py
daplis/functions/compact_share.py
daplis/functions/cross_talk.py
daplis/functions/data_quality.py
daplis/functions/delta_t.py
daplis/functions/fits.py
daplis/functions/mp_analysis.py
daplis/functions/sensor_plot.py
daplis/functions/unpack.py
daplis/functions/utils.py
daplis/params/__init__.py
daplis/params/calibration_data/Offset_A5_#36_2212b.npy
daplis/params/calibration_data/Offset_B7d_#28_2212b.npy
daplis/params/calibration_data/Offset_B7d_#28_2212s.npy
daplis/params/calibration_data/Offset_NL11_#33_2212b.npy
daplis/params/calibration_data/Offset_NL11_#33_2212s.npy
daplis/params/calibration_data/TDC_A5_#36_2212b.csv
daplis/params/calibration_data/TDC_B7d_#28_2212b.csv
daplis/params/calibration_data/TDC_B7d_#28_2212s.csv
daplis/params/calibration_data/TDC_D2b_#4_2212s.csv
daplis/params/calibration_data/TDC_NL11_#21_2212b.csv
daplis/params/calibration_data/TDC_NL11_#21_2212s.csv
daplis/params/calibration_data/TDC_NL11_#33_2212b.csv
daplis/params/calibration_data/TDC_NL11_#33_2212s.csv
daplis/params/masks/mask_A5_#36.txt
daplis/params/masks/mask_B7d_#28.txt
daplis/params/masks/mask_D2b_#4.txt
daplis/params/masks/mask_NL11_#21.txt
daplis/params/masks/mask_NL11_#33.txt
daplis-1.3.1.dist-info/licenses/LICENSE
daplis-1.3.1.dist-info/METADATA
daplis-1.3.1.dist-info/WHEEL
daplis-1.3.1.dist-info/top_level.txt
daplis-1.3.1.dist-info/RECORD
