Metadata-Version: 2.4
Name: daplis
Version: 1.3.1
Summary: Data Analysis Package for LInoSpad
Author-email: Sergei Kulkov <sergei.kulkov23@gmail.com>
License: MIT
Project-URL: Homepage, https://github.com/rngKomorebi/daplis
Keywords: timestamp,analysis,LinoSPAD2
Classifier: Programming Language :: Python :: 3.8
Classifier: Programming Language :: Python :: 3.9
Classifier: Programming Language :: Python :: 3.10
Classifier: Programming Language :: Python :: 3.11
Classifier: Programming Language :: Python :: 3.12
Classifier: Programming Language :: Python :: 3.13
Requires-Python: >=3.8
License-File: LICENSE
Requires-Dist: lmfit>=0.9.1
Requires-Dist: matplotlib>=3.5.0
Requires-Dist: numpy>=1.22.4
Requires-Dist: pandas>=1.4.0
Requires-Dist: pyarrow>=17.0.0
Requires-Dist: scipy>=1.7.0
Requires-Dist: seaborn>=0.9.0
Requires-Dist: tqdm>=4.67.0
Dynamic: license-file
